{
  "real_tick": 65,
  "timestamp": "2026-04-26T10:10:46Z",
  "phase": {
    "name": "event_peak",
    "label": "Pic d'affluence",
    "color": "#ef4444",
    "density_range": [
      0.7,
      0.95
    ]
  },
  "gates": [
    {
      "id": "G1",
      "name": "Entrée Nord-Ouest",
      "lat": 14.6952,
      "lng": -17.4458,
      "capacity": 800,
      "density": 0.6446,
      "crowd_count": 516,
      "level": "high",
      "color": "#f97316"
    },
    {
      "id": "G2",
      "name": "Entrée Nord",
      "lat": 14.6953,
      "lng": -17.4441,
      "capacity": 600,
      "density": 0.6945,
      "crowd_count": 417,
      "level": "high",
      "color": "#f97316"
    },
    {
      "id": "G3",
      "name": "Entrée Nord-Est",
      "lat": 14.6952,
      "lng": -17.4424,
      "capacity": 700,
      "density": 0.5949,
      "crowd_count": 416,
      "level": "high",
      "color": "#f97316"
    },
    {
      "id": "G4",
      "name": "Entrée Est",
      "lat": 14.6937,
      "lng": -17.4419,
      "capacity": 500,
      "density": 0.6133,
      "crowd_count": 307,
      "level": "high",
      "color": "#f97316"
    },
    {
      "id": "G5",
      "name": "Entrée Sud-Est",
      "lat": 14.6921,
      "lng": -17.4424,
      "capacity": 700,
      "density": 0.7835,
      "crowd_count": 548,
      "level": "critical",
      "color": "#ef4444"
    },
    {
      "id": "G6",
      "name": "Entrée Sud",
      "lat": 14.692,
      "lng": -17.4441,
      "capacity": 900,
      "density": 1.0,
      "crowd_count": 900,
      "level": "critical",
      "color": "#ef4444"
    },
    {
      "id": "G7",
      "name": "Entrée Sud-Ouest",
      "lat": 14.6921,
      "lng": -17.4458,
      "capacity": 800,
      "density": 0.916,
      "crowd_count": 733,
      "level": "critical",
      "color": "#ef4444"
    },
    {
      "id": "G8",
      "name": "Entrée Ouest",
      "lat": 14.6937,
      "lng": -17.4462,
      "capacity": 600,
      "density": 0.7101,
      "crowd_count": 426,
      "level": "high",
      "color": "#f97316"
    }
  ],
  "persons": [
    {
      "lat": 14.695117,
      "lng": -17.445912,
      "gate_ref": "G1",
      "color": "#f97316"
    },
    {
      "lat": 14.695056,
      "lng": -17.445964,
      "gate_ref": "G1",
      "color": "#f97316"
    },
    {
      "lat": 14.695223,
      "lng": -17.445908,
      "gate_ref": "G1",
      "color": "#f97316"
    },
    {
      "lat": 14.695617,
      "lng": -17.446266,
      "gate_ref": "G1",
      "color": "#f97316"
    },
    {
      "lat": 14.695634,
      "lng": -17.445282,
      "gate_ref": "G1",
      "color": "#f97316"
    },
    {
      "lat": 14.695314,
      "lng": -17.445956,
      "gate_ref": "G1",
      "color": "#f97316"
    },
    {
      "lat": 14.695808,
      "lng": -17.446333,
      "gate_ref": "G1",
      "color": "#f97316"
    },
    {
      "lat": 14.695471,
      "lng": -17.446179,
      "gate_ref": "G1",
      "color": "#f97316"
    },
    {
      "lat": 14.695243,
      "lng": -17.446049,
      "gate_ref": "G1",
      "color": "#f97316"
    },
    {
      "lat": 14.695413,
      "lng": -17.446045,
      "gate_ref": "G1",
      "color": "#f97316"
    },
    {
      "lat": 14.695935,
      "lng": -17.446421,
      "gate_ref": "G1",
      "color": "#f97316"
    },
    {
      "lat": 14.695424,
      "lng": -17.445976,
      "gate_ref": "G1",
      "color": "#f97316"
    },
    {
      "lat": 14.694692,
      "lng": -17.446239,
      "gate_ref": "G1",
      "color": "#f97316"
    },
    {
      "lat": 14.695145,
      "lng": -17.445867,
      "gate_ref": "G1",
      "color": "#f97316"
    },
    {
      "lat": 14.695222,
      "lng": -17.446032,
      "gate_ref": "G1",
      "color": "#f97316"
    },
    {
      "lat": 14.695503,
      "lng": -17.446074,
      "gate_ref": "G1",
      "color": "#f97316"
    },
    {
      "lat": 14.695496,
      "lng": -17.445955,
      "gate_ref": "G1",
      "color": "#f97316"
    },
    {
      "lat": 14.695301,
      "lng": -17.445722,
      "gate_ref": "G1",
      "color": "#f97316"
    },
    {
      "lat": 14.695339,
      "lng": -17.445643,
      "gate_ref": "G1",
      "color": "#f97316"
    },
    {
      "lat": 14.69532,
      "lng": -17.445768,
      "gate_ref": "G1",
      "color": "#f97316"
    },
    {
      "lat": 14.695206,
      "lng": -17.445884,
      "gate_ref": "G1",
      "color": "#f97316"
    },
    {
      "lat": 14.695147,
      "lng": -17.445915,
      "gate_ref": "G1",
      "color": "#f97316"
    },
    {
      "lat": 14.695516,
      "lng": -17.446254,
      "gate_ref": "G1",
      "color": "#f97316"
    },
    {
      "lat": 14.695314,
      "lng": -17.44602,
      "gate_ref": "G1",
      "color": "#f97316"
    },
    {
      "lat": 14.695233,
      "lng": -17.445872,
      "gate_ref": "G1",
      "color": "#f97316"
    },
    {
      "lat": 14.695329,
      "lng": -17.446141,
      "gate_ref": "G1",
      "color": "#f97316"
    },
    {
      "lat": 14.695953,
      "lng": -17.446504,
      "gate_ref": "G1",
      "color": "#f97316"
    },
    {
      "lat": 14.695483,
      "lng": -17.446334,
      "gate_ref": "G1",
      "color": "#f97316"
    },
    {
      "lat": 14.695251,
      "lng": -17.445777,
      "gate_ref": "G1",
      "color": "#f97316"
    },
    {
      "lat": 14.695393,
      "lng": -17.445542,
      "gate_ref": "G1",
      "color": "#f97316"
    },
    {
      "lat": 14.695895,
      "lng": -17.446658,
      "gate_ref": "G1",
      "color": "#f97316"
    },
    {
      "lat": 14.695133,
      "lng": -17.445913,
      "gate_ref": "G1",
      "color": "#f97316"
    },
    {
      "lat": 14.695648,
      "lng": -17.446353,
      "gate_ref": "G1",
      "color": "#f97316"
    },
    {
      "lat": 14.695187,
      "lng": -17.445817,
      "gate_ref": "G1",
      "color": "#f97316"
    },
    {
      "lat": 14.695567,
      "lng": -17.446024,
      "gate_ref": "G1",
      "color": "#f97316"
    },
    {
      "lat": 14.695598,
      "lng": -17.446046,
      "gate_ref": "G1",
      "color": "#f97316"
    },
    {
      "lat": 14.695886,
      "lng": -17.44656,
      "gate_ref": "G1",
      "color": "#f97316"
    },
    {
      "lat": 14.694876,
      "lng": -17.446253,
      "gate_ref": "G1",
      "color": "#f97316"
    },
    {
      "lat": 14.695295,
      "lng": -17.446023,
      "gate_ref": "G1",
      "color": "#f97316"
    },
    {
      "lat": 14.695202,
      "lng": -17.445808,
      "gate_ref": "G1",
      "color": "#f97316"
    },
    {
      "lat": 14.695217,
      "lng": -17.445954,
      "gate_ref": "G1",
      "color": "#f97316"
    },
    {
      "lat": 14.695974,
      "lng": -17.446587,
      "gate_ref": "G1",
      "color": "#f97316"
    },
    {
      "lat": 14.695694,
      "lng": -17.446388,
      "gate_ref": "G1",
      "color": "#f97316"
    },
    {
      "lat": 14.695136,
      "lng": -17.445923,
      "gate_ref": "G1",
      "color": "#f97316"
    },
    {
      "lat": 14.695302,
      "lng": -17.445631,
      "gate_ref": "G1",
      "color": "#f97316"
    },
    {
      "lat": 14.695171,
      "lng": -17.445833,
      "gate_ref": "G1",
      "color": "#f97316"
    },
    {
      "lat": 14.695444,
      "lng": -17.445881,
      "gate_ref": "G1",
      "color": "#f97316"
    },
    {
      "lat": 14.695413,
      "lng": -17.445837,
      "gate_ref": "G1",
      "color": "#f97316"
    },
    {
      "lat": 14.695489,
      "lng": -17.446105,
      "gate_ref": "G1",
      "color": "#f97316"
    },
    {
      "lat": 14.695647,
      "lng": -17.446192,
      "gate_ref": "G1",
      "color": "#f97316"
    },
    {
      "lat": 14.695428,
      "lng": -17.446101,
      "gate_ref": "G1",
      "color": "#f97316"
    },
    {
      "lat": 14.695851,
      "lng": -17.446579,
      "gate_ref": "G1",
      "color": "#f97316"
    },
    {
      "lat": 14.695707,
      "lng": -17.445363,
      "gate_ref": "G1",
      "color": "#f97316"
    },
    {
      "lat": 14.695498,
      "lng": -17.446172,
      "gate_ref": "G1",
      "color": "#f97316"
    },
    {
      "lat": 14.695199,
      "lng": -17.445958,
      "gate_ref": "G1",
      "color": "#f97316"
    },
    {
      "lat": 14.695275,
      "lng": -17.445786,
      "gate_ref": "G1",
      "color": "#f97316"
    },
    {
      "lat": 14.695799,
      "lng": -17.446627,
      "gate_ref": "G1",
      "color": "#f97316"
    },
    {
      "lat": 14.695976,
      "lng": -17.446533,
      "gate_ref": "G1",
      "color": "#f97316"
    },
    {
      "lat": 14.694956,
      "lng": -17.446146,
      "gate_ref": "G1",
      "color": "#f97316"
    },
    {
      "lat": 14.695202,
      "lng": -17.445874,
      "gate_ref": "G1",
      "color": "#f97316"
    },
    {
      "lat": 14.695635,
      "lng": -17.44638,
      "gate_ref": "G1",
      "color": "#f97316"
    },
    {
      "lat": 14.695368,
      "lng": -17.445784,
      "gate_ref": "G1",
      "color": "#f97316"
    },
    {
      "lat": 14.695492,
      "lng": -17.446301,
      "gate_ref": "G1",
      "color": "#f97316"
    },
    {
      "lat": 14.695881,
      "lng": -17.446579,
      "gate_ref": "G1",
      "color": "#f97316"
    },
    {
      "lat": 14.695948,
      "lng": -17.446545,
      "gate_ref": "G1",
      "color": "#f97316"
    },
    {
      "lat": 14.694774,
      "lng": -17.446113,
      "gate_ref": "G1",
      "color": "#f97316"
    },
    {
      "lat": 14.695004,
      "lng": -17.445879,
      "gate_ref": "G1",
      "color": "#f97316"
    },
    {
      "lat": 14.695462,
      "lng": -17.445889,
      "gate_ref": "G1",
      "color": "#f97316"
    },
    {
      "lat": 14.695962,
      "lng": -17.446566,
      "gate_ref": "G1",
      "color": "#f97316"
    },
    {
      "lat": 14.695527,
      "lng": -17.445978,
      "gate_ref": "G1",
      "color": "#f97316"
    },
    {
      "lat": 14.69567,
      "lng": -17.446518,
      "gate_ref": "G1",
      "color": "#f97316"
    },
    {
      "lat": 14.69578,
      "lng": -17.446589,
      "gate_ref": "G1",
      "color": "#f97316"
    },
    {
      "lat": 14.695817,
      "lng": -17.44636,
      "gate_ref": "G1",
      "color": "#f97316"
    },
    {
      "lat": 14.695217,
      "lng": -17.445785,
      "gate_ref": "G1",
      "color": "#f97316"
    },
    {
      "lat": 14.695462,
      "lng": -17.445952,
      "gate_ref": "G1",
      "color": "#f97316"
    },
    {
      "lat": 14.695711,
      "lng": -17.446458,
      "gate_ref": "G1",
      "color": "#f97316"
    },
    {
      "lat": 14.695337,
      "lng": -17.445892,
      "gate_ref": "G1",
      "color": "#f97316"
    },
    {
      "lat": 14.696377,
      "lng": -17.444216,
      "gate_ref": "G2",
      "color": "#f97316"
    },
    {
      "lat": 14.695515,
      "lng": -17.444022,
      "gate_ref": "G2",
      "color": "#f97316"
    },
    {
      "lat": 14.695586,
      "lng": -17.443964,
      "gate_ref": "G2",
      "color": "#f97316"
    },
    {
      "lat": 14.695323,
      "lng": -17.444052,
      "gate_ref": "G2",
      "color": "#f97316"
    },
    {
      "lat": 14.695372,
      "lng": -17.444022,
      "gate_ref": "G2",
      "color": "#f97316"
    },
    {
      "lat": 14.695997,
      "lng": -17.444186,
      "gate_ref": "G2",
      "color": "#f97316"
    },
    {
      "lat": 14.695469,
      "lng": -17.444113,
      "gate_ref": "G2",
      "color": "#f97316"
    },
    {
      "lat": 14.695306,
      "lng": -17.44414,
      "gate_ref": "G2",
      "color": "#f97316"
    },
    {
      "lat": 14.695711,
      "lng": -17.444142,
      "gate_ref": "G2",
      "color": "#f97316"
    },
    {
      "lat": 14.695731,
      "lng": -17.444139,
      "gate_ref": "G2",
      "color": "#f97316"
    },
    {
      "lat": 14.69542,
      "lng": -17.444229,
      "gate_ref": "G2",
      "color": "#f97316"
    },
    {
      "lat": 14.695418,
      "lng": -17.444074,
      "gate_ref": "G2",
      "color": "#f97316"
    },
    {
      "lat": 14.695298,
      "lng": -17.44434,
      "gate_ref": "G2",
      "color": "#f97316"
    },
    {
      "lat": 14.696297,
      "lng": -17.444241,
      "gate_ref": "G2",
      "color": "#f97316"
    },
    {
      "lat": 14.695934,
      "lng": -17.444022,
      "gate_ref": "G2",
      "color": "#f97316"
    },
    {
      "lat": 14.696105,
      "lng": -17.444029,
      "gate_ref": "G2",
      "color": "#f97316"
    },
    {
      "lat": 14.695413,
      "lng": -17.443998,
      "gate_ref": "G2",
      "color": "#f97316"
    },
    {
      "lat": 14.695776,
      "lng": -17.444179,
      "gate_ref": "G2",
      "color": "#f97316"
    },
    {
      "lat": 14.696146,
      "lng": -17.44402,
      "gate_ref": "G2",
      "color": "#f97316"
    },
    {
      "lat": 14.695699,
      "lng": -17.444072,
      "gate_ref": "G2",
      "color": "#f97316"
    },
    {
      "lat": 14.695879,
      "lng": -17.444227,
      "gate_ref": "G2",
      "color": "#f97316"
    },
    {
      "lat": 14.69583,
      "lng": -17.444136,
      "gate_ref": "G2",
      "color": "#f97316"
    },
    {
      "lat": 14.695565,
      "lng": -17.443964,
      "gate_ref": "G2",
      "color": "#f97316"
    },
    {
      "lat": 14.695424,
      "lng": -17.444037,
      "gate_ref": "G2",
      "color": "#f97316"
    },
    {
      "lat": 14.695364,
      "lng": -17.444237,
      "gate_ref": "G2",
      "color": "#f97316"
    },
    {
      "lat": 14.695773,
      "lng": -17.444221,
      "gate_ref": "G2",
      "color": "#f97316"
    },
    {
      "lat": 14.696264,
      "lng": -17.444059,
      "gate_ref": "G2",
      "color": "#f97316"
    },
    {
      "lat": 14.695745,
      "lng": -17.444047,
      "gate_ref": "G2",
      "color": "#f97316"
    },
    {
      "lat": 14.695627,
      "lng": -17.443974,
      "gate_ref": "G2",
      "color": "#f97316"
    },
    {
      "lat": 14.695792,
      "lng": -17.444222,
      "gate_ref": "G2",
      "color": "#f97316"
    },
    {
      "lat": 14.696293,
      "lng": -17.443994,
      "gate_ref": "G2",
      "color": "#f97316"
    },
    {
      "lat": 14.696087,
      "lng": -17.444043,
      "gate_ref": "G2",
      "color": "#f97316"
    },
    {
      "lat": 14.695912,
      "lng": -17.44421,
      "gate_ref": "G2",
      "color": "#f97316"
    },
    {
      "lat": 14.695342,
      "lng": -17.444191,
      "gate_ref": "G2",
      "color": "#f97316"
    },
    {
      "lat": 14.696074,
      "lng": -17.444199,
      "gate_ref": "G2",
      "color": "#f97316"
    },
    {
      "lat": 14.695236,
      "lng": -17.444679,
      "gate_ref": "G2",
      "color": "#f97316"
    },
    {
      "lat": 14.696243,
      "lng": -17.443974,
      "gate_ref": "G2",
      "color": "#f97316"
    },
    {
      "lat": 14.696145,
      "lng": -17.44424,
      "gate_ref": "G2",
      "color": "#f97316"
    },
    {
      "lat": 14.695639,
      "lng": -17.444156,
      "gate_ref": "G2",
      "color": "#f97316"
    },
    {
      "lat": 14.69554,
      "lng": -17.443982,
      "gate_ref": "G2",
      "color": "#f97316"
    },
    {
      "lat": 14.695406,
      "lng": -17.443964,
      "gate_ref": "G2",
      "color": "#f97316"
    },
    {
      "lat": 14.696356,
      "lng": -17.444006,
      "gate_ref": "G2",
      "color": "#f97316"
    },
    {
      "lat": 14.695331,
      "lng": -17.443967,
      "gate_ref": "G2",
      "color": "#f97316"
    },
    {
      "lat": 14.695355,
      "lng": -17.443914,
      "gate_ref": "G2",
      "color": "#f97316"
    },
    {
      "lat": 14.696163,
      "lng": -17.44417,
      "gate_ref": "G2",
      "color": "#f97316"
    },
    {
      "lat": 14.695275,
      "lng": -17.443974,
      "gate_ref": "G2",
      "color": "#f97316"
    },
    {
      "lat": 14.695643,
      "lng": -17.444057,
      "gate_ref": "G2",
      "color": "#f97316"
    },
    {
      "lat": 14.69594,
      "lng": -17.44411,
      "gate_ref": "G2",
      "color": "#f97316"
    },
    {
      "lat": 14.695314,
      "lng": -17.44407,
      "gate_ref": "G2",
      "color": "#f97316"
    },
    {
      "lat": 14.695812,
      "lng": -17.443985,
      "gate_ref": "G2",
      "color": "#f97316"
    },
    {
      "lat": 14.696328,
      "lng": -17.444191,
      "gate_ref": "G2",
      "color": "#f97316"
    },
    {
      "lat": 14.695334,
      "lng": -17.444228,
      "gate_ref": "G2",
      "color": "#f97316"
    },
    {
      "lat": 14.696123,
      "lng": -17.44418,
      "gate_ref": "G2",
      "color": "#f97316"
    },
    {
      "lat": 14.695972,
      "lng": -17.444102,
      "gate_ref": "G2",
      "color": "#f97316"
    },
    {
      "lat": 14.695374,
      "lng": -17.44419,
      "gate_ref": "G2",
      "color": "#f97316"
    },
    {
      "lat": 14.695698,
      "lng": -17.444202,
      "gate_ref": "G2",
      "color": "#f97316"
    },
    {
      "lat": 14.695427,
      "lng": -17.443674,
      "gate_ref": "G2",
      "color": "#f97316"
    },
    {
      "lat": 14.695652,
      "lng": -17.443959,
      "gate_ref": "G2",
      "color": "#f97316"
    },
    {
      "lat": 14.695398,
      "lng": -17.444683,
      "gate_ref": "G2",
      "color": "#f97316"
    },
    {
      "lat": 14.696227,
      "lng": -17.443972,
      "gate_ref": "G2",
      "color": "#f97316"
    },
    {
      "lat": 14.695845,
      "lng": -17.444184,
      "gate_ref": "G2",
      "color": "#f97316"
    },
    {
      "lat": 14.695362,
      "lng": -17.444227,
      "gate_ref": "G2",
      "color": "#f97316"
    },
    {
      "lat": 14.695503,
      "lng": -17.444132,
      "gate_ref": "G2",
      "color": "#f97316"
    },
    {
      "lat": 14.695387,
      "lng": -17.444223,
      "gate_ref": "G2",
      "color": "#f97316"
    },
    {
      "lat": 14.695411,
      "lng": -17.444043,
      "gate_ref": "G2",
      "color": "#f97316"
    },
    {
      "lat": 14.695729,
      "lng": -17.444233,
      "gate_ref": "G2",
      "color": "#f97316"
    },
    {
      "lat": 14.696017,
      "lng": -17.444199,
      "gate_ref": "G2",
      "color": "#f97316"
    },
    {
      "lat": 14.695799,
      "lng": -17.444105,
      "gate_ref": "G2",
      "color": "#f97316"
    },
    {
      "lat": 14.695518,
      "lng": -17.444219,
      "gate_ref": "G2",
      "color": "#f97316"
    },
    {
      "lat": 14.69579,
      "lng": -17.443989,
      "gate_ref": "G2",
      "color": "#f97316"
    },
    {
      "lat": 14.695895,
      "lng": -17.444221,
      "gate_ref": "G2",
      "color": "#f97316"
    },
    {
      "lat": 14.695941,
      "lng": -17.444028,
      "gate_ref": "G2",
      "color": "#f97316"
    },
    {
      "lat": 14.695947,
      "lng": -17.44399,
      "gate_ref": "G2",
      "color": "#f97316"
    },
    {
      "lat": 14.695389,
      "lng": -17.443975,
      "gate_ref": "G2",
      "color": "#f97316"
    },
    {
      "lat": 14.695813,
      "lng": -17.444213,
      "gate_ref": "G2",
      "color": "#f97316"
    },
    {
      "lat": 14.695342,
      "lng": -17.443963,
      "gate_ref": "G2",
      "color": "#f97316"
    },
    {
      "lat": 14.695917,
      "lng": -17.444054,
      "gate_ref": "G2",
      "color": "#f97316"
    },
    {
      "lat": 14.695795,
      "lng": -17.444144,
      "gate_ref": "G2",
      "color": "#f97316"
    },
    {
      "lat": 14.695706,
      "lng": -17.443993,
      "gate_ref": "G2",
      "color": "#f97316"
    },
    {
      "lat": 14.696168,
      "lng": -17.444157,
      "gate_ref": "G2",
      "color": "#f97316"
    },
    {
      "lat": 14.696396,
      "lng": -17.444162,
      "gate_ref": "G2",
      "color": "#f97316"
    },
    {
      "lat": 14.695663,
      "lng": -17.444233,
      "gate_ref": "G2",
      "color": "#f97316"
    },
    {
      "lat": 14.695411,
      "lng": -17.443992,
      "gate_ref": "G2",
      "color": "#f97316"
    },
    {
      "lat": 14.695828,
      "lng": -17.441476,
      "gate_ref": "G3",
      "color": "#f97316"
    },
    {
      "lat": 14.695595,
      "lng": -17.442152,
      "gate_ref": "G3",
      "color": "#f97316"
    },
    {
      "lat": 14.695328,
      "lng": -17.442287,
      "gate_ref": "G3",
      "color": "#f97316"
    },
    {
      "lat": 14.695388,
      "lng": -17.442173,
      "gate_ref": "G3",
      "color": "#f97316"
    },
    {
      "lat": 14.695878,
      "lng": -17.441813,
      "gate_ref": "G3",
      "color": "#f97316"
    },
    {
      "lat": 14.695908,
      "lng": -17.441667,
      "gate_ref": "G3",
      "color": "#f97316"
    },
    {
      "lat": 14.695643,
      "lng": -17.441798,
      "gate_ref": "G3",
      "color": "#f97316"
    },
    {
      "lat": 14.695273,
      "lng": -17.442352,
      "gate_ref": "G3",
      "color": "#f97316"
    },
    {
      "lat": 14.695456,
      "lng": -17.44264,
      "gate_ref": "G3",
      "color": "#f97316"
    },
    {
      "lat": 14.695287,
      "lng": -17.442454,
      "gate_ref": "G3",
      "color": "#f97316"
    },
    {
      "lat": 14.69599,
      "lng": -17.441634,
      "gate_ref": "G3",
      "color": "#f97316"
    },
    {
      "lat": 14.695617,
      "lng": -17.441722,
      "gate_ref": "G3",
      "color": "#f97316"
    },
    {
      "lat": 14.695236,
      "lng": -17.442304,
      "gate_ref": "G3",
      "color": "#f97316"
    },
    {
      "lat": 14.695411,
      "lng": -17.442147,
      "gate_ref": "G3",
      "color": "#f97316"
    },
    {
      "lat": 14.695499,
      "lng": -17.442033,
      "gate_ref": "G3",
      "color": "#f97316"
    },
    {
      "lat": 14.695739,
      "lng": -17.441998,
      "gate_ref": "G3",
      "color": "#f97316"
    },
    {
      "lat": 14.695346,
      "lng": -17.442137,
      "gate_ref": "G3",
      "color": "#f97316"
    },
    {
      "lat": 14.694745,
      "lng": -17.441998,
      "gate_ref": "G3",
      "color": "#f97316"
    },
    {
      "lat": 14.695292,
      "lng": -17.44211,
      "gate_ref": "G3",
      "color": "#f97316"
    },
    {
      "lat": 14.695341,
      "lng": -17.442563,
      "gate_ref": "G3",
      "color": "#f97316"
    },
    {
      "lat": 14.695658,
      "lng": -17.441901,
      "gate_ref": "G3",
      "color": "#f97316"
    },
    {
      "lat": 14.695248,
      "lng": -17.44238,
      "gate_ref": "G3",
      "color": "#f97316"
    },
    {
      "lat": 14.695232,
      "lng": -17.442342,
      "gate_ref": "G3",
      "color": "#f97316"
    },
    {
      "lat": 14.695417,
      "lng": -17.44224,
      "gate_ref": "G3",
      "color": "#f97316"
    },
    {
      "lat": 14.695144,
      "lng": -17.442268,
      "gate_ref": "G3",
      "color": "#f97316"
    },
    {
      "lat": 14.695421,
      "lng": -17.442244,
      "gate_ref": "G3",
      "color": "#f97316"
    },
    {
      "lat": 14.695642,
      "lng": -17.441723,
      "gate_ref": "G3",
      "color": "#f97316"
    },
    {
      "lat": 14.695176,
      "lng": -17.442372,
      "gate_ref": "G3",
      "color": "#f97316"
    },
    {
      "lat": 14.695345,
      "lng": -17.44242,
      "gate_ref": "G3",
      "color": "#f97316"
    },
    {
      "lat": 14.69575,
      "lng": -17.441762,
      "gate_ref": "G3",
      "color": "#f97316"
    },
    {
      "lat": 14.695314,
      "lng": -17.442454,
      "gate_ref": "G3",
      "color": "#f97316"
    },
    {
      "lat": 14.695916,
      "lng": -17.441635,
      "gate_ref": "G3",
      "color": "#f97316"
    },
    {
      "lat": 14.695433,
      "lng": -17.442316,
      "gate_ref": "G3",
      "color": "#f97316"
    },
    {
      "lat": 14.695334,
      "lng": -17.442313,
      "gate_ref": "G3",
      "color": "#f97316"
    },
    {
      "lat": 14.695564,
      "lng": -17.442149,
      "gate_ref": "G3",
      "color": "#f97316"
    },
    {
      "lat": 14.695911,
      "lng": -17.441635,
      "gate_ref": "G3",
      "color": "#f97316"
    },
    {
      "lat": 14.695489,
      "lng": -17.44225,
      "gate_ref": "G3",
      "color": "#f97316"
    },
    {
      "lat": 14.695632,
      "lng": -17.442073,
      "gate_ref": "G3",
      "color": "#f97316"
    },
    {
      "lat": 14.695301,
      "lng": -17.44248,
      "gate_ref": "G3",
      "color": "#f97316"
    },
    {
      "lat": 14.695877,
      "lng": -17.441616,
      "gate_ref": "G3",
      "color": "#f97316"
    },
    {
      "lat": 14.695859,
      "lng": -17.441841,
      "gate_ref": "G3",
      "color": "#f97316"
    },
    {
      "lat": 14.695243,
      "lng": -17.442256,
      "gate_ref": "G3",
      "color": "#f97316"
    },
    {
      "lat": 14.695887,
      "lng": -17.441758,
      "gate_ref": "G3",
      "color": "#f97316"
    },
    {
      "lat": 14.695229,
      "lng": -17.44223,
      "gate_ref": "G3",
      "color": "#f97316"
    },
    {
      "lat": 14.695402,
      "lng": -17.442351,
      "gate_ref": "G3",
      "color": "#f97316"
    },
    {
      "lat": 14.695265,
      "lng": -17.442453,
      "gate_ref": "G3",
      "color": "#f97316"
    },
    {
      "lat": 14.695717,
      "lng": -17.441795,
      "gate_ref": "G3",
      "color": "#f97316"
    },
    {
      "lat": 14.695308,
      "lng": -17.442266,
      "gate_ref": "G3",
      "color": "#f97316"
    },
    {
      "lat": 14.695384,
      "lng": -17.442528,
      "gate_ref": "G3",
      "color": "#f97316"
    },
    {
      "lat": 14.695396,
      "lng": -17.442387,
      "gate_ref": "G3",
      "color": "#f97316"
    },
    {
      "lat": 14.695392,
      "lng": -17.442668,
      "gate_ref": "G3",
      "color": "#f97316"
    },
    {
      "lat": 14.695445,
      "lng": -17.441921,
      "gate_ref": "G3",
      "color": "#f97316"
    },
    {
      "lat": 14.69534,
      "lng": -17.442166,
      "gate_ref": "G3",
      "color": "#f97316"
    },
    {
      "lat": 14.695598,
      "lng": -17.441904,
      "gate_ref": "G3",
      "color": "#f97316"
    },
    {
      "lat": 14.695447,
      "lng": -17.442284,
      "gate_ref": "G3",
      "color": "#f97316"
    },
    {
      "lat": 14.695771,
      "lng": -17.441898,
      "gate_ref": "G3",
      "color": "#f97316"
    },
    {
      "lat": 14.695685,
      "lng": -17.441982,
      "gate_ref": "G3",
      "color": "#f97316"
    },
    {
      "lat": 14.695735,
      "lng": -17.441859,
      "gate_ref": "G3",
      "color": "#f97316"
    },
    {
      "lat": 14.694951,
      "lng": -17.442169,
      "gate_ref": "G3",
      "color": "#f97316"
    },
    {
      "lat": 14.695816,
      "lng": -17.44186,
      "gate_ref": "G3",
      "color": "#f97316"
    },
    {
      "lat": 14.695347,
      "lng": -17.442198,
      "gate_ref": "G3",
      "color": "#f97316"
    },
    {
      "lat": 14.695714,
      "lng": -17.441974,
      "gate_ref": "G3",
      "color": "#f97316"
    },
    {
      "lat": 14.695199,
      "lng": -17.44238,
      "gate_ref": "G3",
      "color": "#f97316"
    },
    {
      "lat": 14.695196,
      "lng": -17.442324,
      "gate_ref": "G3",
      "color": "#f97316"
    },
    {
      "lat": 14.695545,
      "lng": -17.441856,
      "gate_ref": "G3",
      "color": "#f97316"
    },
    {
      "lat": 14.695036,
      "lng": -17.442094,
      "gate_ref": "G3",
      "color": "#f97316"
    },
    {
      "lat": 14.695532,
      "lng": -17.44185,
      "gate_ref": "G3",
      "color": "#f97316"
    },
    {
      "lat": 14.695252,
      "lng": -17.442159,
      "gate_ref": "G3",
      "color": "#f97316"
    },
    {
      "lat": 14.695202,
      "lng": -17.442394,
      "gate_ref": "G3",
      "color": "#f97316"
    },
    {
      "lat": 14.695243,
      "lng": -17.442352,
      "gate_ref": "G3",
      "color": "#f97316"
    },
    {
      "lat": 14.695673,
      "lng": -17.442031,
      "gate_ref": "G3",
      "color": "#f97316"
    },
    {
      "lat": 14.693748,
      "lng": -17.441586,
      "gate_ref": "G4",
      "color": "#f97316"
    },
    {
      "lat": 14.693663,
      "lng": -17.441765,
      "gate_ref": "G4",
      "color": "#f97316"
    },
    {
      "lat": 14.693619,
      "lng": -17.441648,
      "gate_ref": "G4",
      "color": "#f97316"
    },
    {
      "lat": 14.693681,
      "lng": -17.441789,
      "gate_ref": "G4",
      "color": "#f97316"
    },
    {
      "lat": 14.693571,
      "lng": -17.441767,
      "gate_ref": "G4",
      "color": "#f97316"
    },
    {
      "lat": 14.693631,
      "lng": -17.441362,
      "gate_ref": "G4",
      "color": "#f97316"
    },
    {
      "lat": 14.693734,
      "lng": -17.441304,
      "gate_ref": "G4",
      "color": "#f97316"
    },
    {
      "lat": 14.693988,
      "lng": -17.441945,
      "gate_ref": "G4",
      "color": "#f97316"
    },
    {
      "lat": 14.693696,
      "lng": -17.441202,
      "gate_ref": "G4",
      "color": "#f97316"
    },
    {
      "lat": 14.693645,
      "lng": -17.441816,
      "gate_ref": "G4",
      "color": "#f97316"
    },
    {
      "lat": 14.693715,
      "lng": -17.441822,
      "gate_ref": "G4",
      "color": "#f97316"
    },
    {
      "lat": 14.69371,
      "lng": -17.441775,
      "gate_ref": "G4",
      "color": "#f97316"
    },
    {
      "lat": 14.693752,
      "lng": -17.441891,
      "gate_ref": "G4",
      "color": "#f97316"
    },
    {
      "lat": 14.693574,
      "lng": -17.441899,
      "gate_ref": "G4",
      "color": "#f97316"
    },
    {
      "lat": 14.69367,
      "lng": -17.44187,
      "gate_ref": "G4",
      "color": "#f97316"
    },
    {
      "lat": 14.693239,
      "lng": -17.44176,
      "gate_ref": "G4",
      "color": "#f97316"
    },
    {
      "lat": 14.693807,
      "lng": -17.44135,
      "gate_ref": "G4",
      "color": "#f97316"
    },
    {
      "lat": 14.693562,
      "lng": -17.441779,
      "gate_ref": "G4",
      "color": "#f97316"
    },
    {
      "lat": 14.693631,
      "lng": -17.441828,
      "gate_ref": "G4",
      "color": "#f97316"
    },
    {
      "lat": 14.693613,
      "lng": -17.441767,
      "gate_ref": "G4",
      "color": "#f97316"
    },
    {
      "lat": 14.693597,
      "lng": -17.441432,
      "gate_ref": "G4",
      "color": "#f97316"
    },
    {
      "lat": 14.693659,
      "lng": -17.441828,
      "gate_ref": "G4",
      "color": "#f97316"
    },
    {
      "lat": 14.693609,
      "lng": -17.441238,
      "gate_ref": "G4",
      "color": "#f97316"
    },
    {
      "lat": 14.6936,
      "lng": -17.440904,
      "gate_ref": "G4",
      "color": "#f97316"
    },
    {
      "lat": 14.69372,
      "lng": -17.44142,
      "gate_ref": "G4",
      "color": "#f97316"
    },
    {
      "lat": 14.693587,
      "lng": -17.440959,
      "gate_ref": "G4",
      "color": "#f97316"
    },
    {
      "lat": 14.693666,
      "lng": -17.441466,
      "gate_ref": "G4",
      "color": "#f97316"
    },
    {
      "lat": 14.694148,
      "lng": -17.441992,
      "gate_ref": "G4",
      "color": "#f97316"
    },
    {
      "lat": 14.693701,
      "lng": -17.441545,
      "gate_ref": "G4",
      "color": "#f97316"
    },
    {
      "lat": 14.693686,
      "lng": -17.441567,
      "gate_ref": "G4",
      "color": "#f97316"
    },
    {
      "lat": 14.693673,
      "lng": -17.441885,
      "gate_ref": "G4",
      "color": "#f97316"
    },
    {
      "lat": 14.694015,
      "lng": -17.441943,
      "gate_ref": "G4",
      "color": "#f97316"
    },
    {
      "lat": 14.693573,
      "lng": -17.440792,
      "gate_ref": "G4",
      "color": "#f97316"
    },
    {
      "lat": 14.693425,
      "lng": -17.44195,
      "gate_ref": "G4",
      "color": "#f97316"
    },
    {
      "lat": 14.693813,
      "lng": -17.441895,
      "gate_ref": "G4",
      "color": "#f97316"
    },
    {
      "lat": 14.69358,
      "lng": -17.441225,
      "gate_ref": "G4",
      "color": "#f97316"
    },
    {
      "lat": 14.693776,
      "lng": -17.441809,
      "gate_ref": "G4",
      "color": "#f97316"
    },
    {
      "lat": 14.693876,
      "lng": -17.441876,
      "gate_ref": "G4",
      "color": "#f97316"
    },
    {
      "lat": 14.69368,
      "lng": -17.441438,
      "gate_ref": "G4",
      "color": "#f97316"
    },
    {
      "lat": 14.693746,
      "lng": -17.441124,
      "gate_ref": "G4",
      "color": "#f97316"
    },
    {
      "lat": 14.693827,
      "lng": -17.441826,
      "gate_ref": "G4",
      "color": "#f97316"
    },
    {
      "lat": 14.693822,
      "lng": -17.441148,
      "gate_ref": "G4",
      "color": "#f97316"
    },
    {
      "lat": 14.693644,
      "lng": -17.44093,
      "gate_ref": "G4",
      "color": "#f97316"
    },
    {
      "lat": 14.693574,
      "lng": -17.441864,
      "gate_ref": "G4",
      "color": "#f97316"
    },
    {
      "lat": 14.693577,
      "lng": -17.441864,
      "gate_ref": "G4",
      "color": "#f97316"
    },
    {
      "lat": 14.693046,
      "lng": -17.441808,
      "gate_ref": "G4",
      "color": "#f97316"
    },
    {
      "lat": 14.693811,
      "lng": -17.441305,
      "gate_ref": "G4",
      "color": "#f97316"
    },
    {
      "lat": 14.693677,
      "lng": -17.441747,
      "gate_ref": "G4",
      "color": "#f97316"
    },
    {
      "lat": 14.693573,
      "lng": -17.441352,
      "gate_ref": "G4",
      "color": "#f97316"
    },
    {
      "lat": 14.693827,
      "lng": -17.441585,
      "gate_ref": "G4",
      "color": "#f97316"
    },
    {
      "lat": 14.693673,
      "lng": -17.44133,
      "gate_ref": "G4",
      "color": "#f97316"
    },
    {
      "lat": 14.693887,
      "lng": -17.441904,
      "gate_ref": "G4",
      "color": "#f97316"
    },
    {
      "lat": 14.693781,
      "lng": -17.441629,
      "gate_ref": "G4",
      "color": "#f97316"
    },
    {
      "lat": 14.693704,
      "lng": -17.440973,
      "gate_ref": "G4",
      "color": "#f97316"
    },
    {
      "lat": 14.693789,
      "lng": -17.441263,
      "gate_ref": "G4",
      "color": "#f97316"
    },
    {
      "lat": 14.693586,
      "lng": -17.441384,
      "gate_ref": "G4",
      "color": "#f97316"
    },
    {
      "lat": 14.693588,
      "lng": -17.441616,
      "gate_ref": "G4",
      "color": "#f97316"
    },
    {
      "lat": 14.693759,
      "lng": -17.441908,
      "gate_ref": "G4",
      "color": "#f97316"
    },
    {
      "lat": 14.693759,
      "lng": -17.44098,
      "gate_ref": "G4",
      "color": "#f97316"
    },
    {
      "lat": 14.693788,
      "lng": -17.441603,
      "gate_ref": "G4",
      "color": "#f97316"
    },
    {
      "lat": 14.693623,
      "lng": -17.441131,
      "gate_ref": "G4",
      "color": "#f97316"
    },
    {
      "lat": 14.69362,
      "lng": -17.441732,
      "gate_ref": "G4",
      "color": "#f97316"
    },
    {
      "lat": 14.693779,
      "lng": -17.441376,
      "gate_ref": "G4",
      "color": "#f97316"
    },
    {
      "lat": 14.693568,
      "lng": -17.441199,
      "gate_ref": "G4",
      "color": "#f97316"
    },
    {
      "lat": 14.6938,
      "lng": -17.441702,
      "gate_ref": "G4",
      "color": "#f97316"
    },
    {
      "lat": 14.693683,
      "lng": -17.441835,
      "gate_ref": "G4",
      "color": "#f97316"
    },
    {
      "lat": 14.6936,
      "lng": -17.441686,
      "gate_ref": "G4",
      "color": "#f97316"
    },
    {
      "lat": 14.693736,
      "lng": -17.441565,
      "gate_ref": "G4",
      "color": "#f97316"
    },
    {
      "lat": 14.6937,
      "lng": -17.441851,
      "gate_ref": "G4",
      "color": "#f97316"
    },
    {
      "lat": 14.693734,
      "lng": -17.441352,
      "gate_ref": "G4",
      "color": "#f97316"
    },
    {
      "lat": 14.693569,
      "lng": -17.441378,
      "gate_ref": "G4",
      "color": "#f97316"
    },
    {
      "lat": 14.693614,
      "lng": -17.441896,
      "gate_ref": "G4",
      "color": "#f97316"
    },
    {
      "lat": 14.693694,
      "lng": -17.441853,
      "gate_ref": "G4",
      "color": "#f97316"
    },
    {
      "lat": 14.693572,
      "lng": -17.441038,
      "gate_ref": "G4",
      "color": "#f97316"
    },
    {
      "lat": 14.691789,
      "lng": -17.442252,
      "gate_ref": "G5",
      "color": "#ef4444"
    },
    {
      "lat": 14.691404,
      "lng": -17.441576,
      "gate_ref": "G5",
      "color": "#ef4444"
    },
    {
      "lat": 14.691485,
      "lng": -17.441711,
      "gate_ref": "G5",
      "color": "#ef4444"
    },
    {
      "lat": 14.691731,
      "lng": -17.442098,
      "gate_ref": "G5",
      "color": "#ef4444"
    },
    {
      "lat": 14.691787,
      "lng": -17.442254,
      "gate_ref": "G5",
      "color": "#ef4444"
    },
    {
      "lat": 14.691865,
      "lng": -17.442752,
      "gate_ref": "G5",
      "color": "#ef4444"
    },
    {
      "lat": 14.691587,
      "lng": -17.442787,
      "gate_ref": "G5",
      "color": "#ef4444"
    },
    {
      "lat": 14.691446,
      "lng": -17.441521,
      "gate_ref": "G5",
      "color": "#ef4444"
    },
    {
      "lat": 14.69195,
      "lng": -17.442369,
      "gate_ref": "G5",
      "color": "#ef4444"
    },
    {
      "lat": 14.692094,
      "lng": -17.442323,
      "gate_ref": "G5",
      "color": "#ef4444"
    },
    {
      "lat": 14.691867,
      "lng": -17.442199,
      "gate_ref": "G5",
      "color": "#ef4444"
    },
    {
      "lat": 14.691957,
      "lng": -17.442605,
      "gate_ref": "G5",
      "color": "#ef4444"
    },
    {
      "lat": 14.692062,
      "lng": -17.442339,
      "gate_ref": "G5",
      "color": "#ef4444"
    },
    {
      "lat": 14.691873,
      "lng": -17.442142,
      "gate_ref": "G5",
      "color": "#ef4444"
    },
    {
      "lat": 14.691873,
      "lng": -17.442135,
      "gate_ref": "G5",
      "color": "#ef4444"
    },
    {
      "lat": 14.691699,
      "lng": -17.442002,
      "gate_ref": "G5",
      "color": "#ef4444"
    },
    {
      "lat": 14.692096,
      "lng": -17.442403,
      "gate_ref": "G5",
      "color": "#ef4444"
    },
    {
      "lat": 14.692103,
      "lng": -17.442375,
      "gate_ref": "G5",
      "color": "#ef4444"
    },
    {
      "lat": 14.69171,
      "lng": -17.442621,
      "gate_ref": "G5",
      "color": "#ef4444"
    },
    {
      "lat": 14.691447,
      "lng": -17.441885,
      "gate_ref": "G5",
      "color": "#ef4444"
    },
    {
      "lat": 14.692193,
      "lng": -17.442376,
      "gate_ref": "G5",
      "color": "#ef4444"
    },
    {
      "lat": 14.691311,
      "lng": -17.441681,
      "gate_ref": "G5",
      "color": "#ef4444"
    },
    {
      "lat": 14.691865,
      "lng": -17.442304,
      "gate_ref": "G5",
      "color": "#ef4444"
    },
    {
      "lat": 14.691997,
      "lng": -17.442224,
      "gate_ref": "G5",
      "color": "#ef4444"
    },
    {
      "lat": 14.691981,
      "lng": -17.442326,
      "gate_ref": "G5",
      "color": "#ef4444"
    },
    {
      "lat": 14.69227,
      "lng": -17.442104,
      "gate_ref": "G5",
      "color": "#ef4444"
    },
    {
      "lat": 14.691873,
      "lng": -17.442098,
      "gate_ref": "G5",
      "color": "#ef4444"
    },
    {
      "lat": 14.692044,
      "lng": -17.442669,
      "gate_ref": "G5",
      "color": "#ef4444"
    },
    {
      "lat": 14.692052,
      "lng": -17.442292,
      "gate_ref": "G5",
      "color": "#ef4444"
    },
    {
      "lat": 14.691878,
      "lng": -17.442182,
      "gate_ref": "G5",
      "color": "#ef4444"
    },
    {
      "lat": 14.691906,
      "lng": -17.442065,
      "gate_ref": "G5",
      "color": "#ef4444"
    },
    {
      "lat": 14.69211,
      "lng": -17.442336,
      "gate_ref": "G5",
      "color": "#ef4444"
    },
    {
      "lat": 14.691934,
      "lng": -17.442334,
      "gate_ref": "G5",
      "color": "#ef4444"
    },
    {
      "lat": 14.691681,
      "lng": -17.441838,
      "gate_ref": "G5",
      "color": "#ef4444"
    },
    {
      "lat": 14.691595,
      "lng": -17.441891,
      "gate_ref": "G5",
      "color": "#ef4444"
    },
    {
      "lat": 14.691929,
      "lng": -17.442377,
      "gate_ref": "G5",
      "color": "#ef4444"
    },
    {
      "lat": 14.692102,
      "lng": -17.442208,
      "gate_ref": "G5",
      "color": "#ef4444"
    },
    {
      "lat": 14.691647,
      "lng": -17.442724,
      "gate_ref": "G5",
      "color": "#ef4444"
    },
    {
      "lat": 14.691922,
      "lng": -17.442136,
      "gate_ref": "G5",
      "color": "#ef4444"
    },
    {
      "lat": 14.692089,
      "lng": -17.442234,
      "gate_ref": "G5",
      "color": "#ef4444"
    },
    {
      "lat": 14.691949,
      "lng": -17.4421,
      "gate_ref": "G5",
      "color": "#ef4444"
    },
    {
      "lat": 14.691545,
      "lng": -17.441643,
      "gate_ref": "G5",
      "color": "#ef4444"
    },
    {
      "lat": 14.691422,
      "lng": -17.4417,
      "gate_ref": "G5",
      "color": "#ef4444"
    },
    {
      "lat": 14.692031,
      "lng": -17.44225,
      "gate_ref": "G5",
      "color": "#ef4444"
    },
    {
      "lat": 14.692254,
      "lng": -17.442342,
      "gate_ref": "G5",
      "color": "#ef4444"
    },
    {
      "lat": 14.691467,
      "lng": -17.44174,
      "gate_ref": "G5",
      "color": "#ef4444"
    },
    {
      "lat": 14.691751,
      "lng": -17.441944,
      "gate_ref": "G5",
      "color": "#ef4444"
    },
    {
      "lat": 14.69198,
      "lng": -17.442364,
      "gate_ref": "G5",
      "color": "#ef4444"
    },
    {
      "lat": 14.692051,
      "lng": -17.442323,
      "gate_ref": "G5",
      "color": "#ef4444"
    },
    {
      "lat": 14.692136,
      "lng": -17.442299,
      "gate_ref": "G5",
      "color": "#ef4444"
    },
    {
      "lat": 14.691519,
      "lng": -17.441764,
      "gate_ref": "G5",
      "color": "#ef4444"
    },
    {
      "lat": 14.691754,
      "lng": -17.441994,
      "gate_ref": "G5",
      "color": "#ef4444"
    },
    {
      "lat": 14.69215,
      "lng": -17.442343,
      "gate_ref": "G5",
      "color": "#ef4444"
    },
    {
      "lat": 14.691714,
      "lng": -17.441865,
      "gate_ref": "G5",
      "color": "#ef4444"
    },
    {
      "lat": 14.691977,
      "lng": -17.442297,
      "gate_ref": "G5",
      "color": "#ef4444"
    },
    {
      "lat": 14.691528,
      "lng": -17.441918,
      "gate_ref": "G5",
      "color": "#ef4444"
    },
    {
      "lat": 14.691432,
      "lng": -17.441672,
      "gate_ref": "G5",
      "color": "#ef4444"
    },
    {
      "lat": 14.691871,
      "lng": -17.442458,
      "gate_ref": "G5",
      "color": "#ef4444"
    },
    {
      "lat": 14.692084,
      "lng": -17.442559,
      "gate_ref": "G5",
      "color": "#ef4444"
    },
    {
      "lat": 14.692011,
      "lng": -17.442489,
      "gate_ref": "G5",
      "color": "#ef4444"
    },
    {
      "lat": 14.691956,
      "lng": -17.442156,
      "gate_ref": "G5",
      "color": "#ef4444"
    },
    {
      "lat": 14.692086,
      "lng": -17.442331,
      "gate_ref": "G5",
      "color": "#ef4444"
    },
    {
      "lat": 14.692647,
      "lng": -17.442041,
      "gate_ref": "G5",
      "color": "#ef4444"
    },
    {
      "lat": 14.691755,
      "lng": -17.441951,
      "gate_ref": "G5",
      "color": "#ef4444"
    },
    {
      "lat": 14.692019,
      "lng": -17.442367,
      "gate_ref": "G5",
      "color": "#ef4444"
    },
    {
      "lat": 14.692096,
      "lng": -17.44224,
      "gate_ref": "G5",
      "color": "#ef4444"
    },
    {
      "lat": 14.692013,
      "lng": -17.442372,
      "gate_ref": "G5",
      "color": "#ef4444"
    },
    {
      "lat": 14.692004,
      "lng": -17.44239,
      "gate_ref": "G5",
      "color": "#ef4444"
    },
    {
      "lat": 14.691718,
      "lng": -17.441903,
      "gate_ref": "G5",
      "color": "#ef4444"
    },
    {
      "lat": 14.692056,
      "lng": -17.44237,
      "gate_ref": "G5",
      "color": "#ef4444"
    },
    {
      "lat": 14.691638,
      "lng": -17.442114,
      "gate_ref": "G5",
      "color": "#ef4444"
    },
    {
      "lat": 14.691907,
      "lng": -17.442267,
      "gate_ref": "G5",
      "color": "#ef4444"
    },
    {
      "lat": 14.69175,
      "lng": -17.4429,
      "gate_ref": "G5",
      "color": "#ef4444"
    },
    {
      "lat": 14.692092,
      "lng": -17.442331,
      "gate_ref": "G5",
      "color": "#ef4444"
    },
    {
      "lat": 14.691933,
      "lng": -17.442415,
      "gate_ref": "G5",
      "color": "#ef4444"
    },
    {
      "lat": 14.691614,
      "lng": -17.441881,
      "gate_ref": "G5",
      "color": "#ef4444"
    },
    {
      "lat": 14.691891,
      "lng": -17.442107,
      "gate_ref": "G5",
      "color": "#ef4444"
    },
    {
      "lat": 14.691615,
      "lng": -17.441743,
      "gate_ref": "G5",
      "color": "#ef4444"
    },
    {
      "lat": 14.691802,
      "lng": -17.442175,
      "gate_ref": "G5",
      "color": "#ef4444"
    },
    {
      "lat": 14.691984,
      "lng": -17.44229,
      "gate_ref": "G5",
      "color": "#ef4444"
    },
    {
      "lat": 14.691546,
      "lng": -17.441834,
      "gate_ref": "G5",
      "color": "#ef4444"
    },
    {
      "lat": 14.691964,
      "lng": -17.442244,
      "gate_ref": "G5",
      "color": "#ef4444"
    },
    {
      "lat": 14.691424,
      "lng": -17.441848,
      "gate_ref": "G5",
      "color": "#ef4444"
    },
    {
      "lat": 14.692035,
      "lng": -17.442382,
      "gate_ref": "G5",
      "color": "#ef4444"
    },
    {
      "lat": 14.692076,
      "lng": -17.442248,
      "gate_ref": "G5",
      "color": "#ef4444"
    },
    {
      "lat": 14.692537,
      "lng": -17.441838,
      "gate_ref": "G5",
      "color": "#ef4444"
    },
    {
      "lat": 14.691462,
      "lng": -17.441734,
      "gate_ref": "G5",
      "color": "#ef4444"
    },
    {
      "lat": 14.691522,
      "lng": -17.441864,
      "gate_ref": "G5",
      "color": "#ef4444"
    },
    {
      "lat": 14.691666,
      "lng": -17.441869,
      "gate_ref": "G5",
      "color": "#ef4444"
    },
    {
      "lat": 14.691917,
      "lng": -17.442405,
      "gate_ref": "G5",
      "color": "#ef4444"
    },
    {
      "lat": 14.691863,
      "lng": -17.442124,
      "gate_ref": "G5",
      "color": "#ef4444"
    },
    {
      "lat": 14.691862,
      "lng": -17.442266,
      "gate_ref": "G5",
      "color": "#ef4444"
    },
    {
      "lat": 14.691968,
      "lng": -17.442181,
      "gate_ref": "G5",
      "color": "#ef4444"
    },
    {
      "lat": 14.692087,
      "lng": -17.44226,
      "gate_ref": "G5",
      "color": "#ef4444"
    },
    {
      "lat": 14.691676,
      "lng": -17.444061,
      "gate_ref": "G6",
      "color": "#ef4444"
    },
    {
      "lat": 14.691886,
      "lng": -17.444034,
      "gate_ref": "G6",
      "color": "#ef4444"
    },
    {
      "lat": 14.691935,
      "lng": -17.444183,
      "gate_ref": "G6",
      "color": "#ef4444"
    },
    {
      "lat": 14.691053,
      "lng": -17.444142,
      "gate_ref": "G6",
      "color": "#ef4444"
    },
    {
      "lat": 14.69202,
      "lng": -17.443446,
      "gate_ref": "G6",
      "color": "#ef4444"
    },
    {
      "lat": 14.691925,
      "lng": -17.443658,
      "gate_ref": "G6",
      "color": "#ef4444"
    },
    {
      "lat": 14.691605,
      "lng": -17.443982,
      "gate_ref": "G6",
      "color": "#ef4444"
    },
    {
      "lat": 14.691817,
      "lng": -17.444227,
      "gate_ref": "G6",
      "color": "#ef4444"
    },
    {
      "lat": 14.69199,
      "lng": -17.443995,
      "gate_ref": "G6",
      "color": "#ef4444"
    },
    {
      "lat": 14.691223,
      "lng": -17.44412,
      "gate_ref": "G6",
      "color": "#ef4444"
    },
    {
      "lat": 14.69194,
      "lng": -17.444033,
      "gate_ref": "G6",
      "color": "#ef4444"
    },
    {
      "lat": 14.691932,
      "lng": -17.444025,
      "gate_ref": "G6",
      "color": "#ef4444"
    },
    {
      "lat": 14.691999,
      "lng": -17.444126,
      "gate_ref": "G6",
      "color": "#ef4444"
    },
    {
      "lat": 14.691408,
      "lng": -17.444187,
      "gate_ref": "G6",
      "color": "#ef4444"
    },
    {
      "lat": 14.691955,
      "lng": -17.444239,
      "gate_ref": "G6",
      "color": "#ef4444"
    },
    {
      "lat": 14.691495,
      "lng": -17.443961,
      "gate_ref": "G6",
      "color": "#ef4444"
    },
    {
      "lat": 14.69167,
      "lng": -17.444175,
      "gate_ref": "G6",
      "color": "#ef4444"
    },
    {
      "lat": 14.6911,
      "lng": -17.444094,
      "gate_ref": "G6",
      "color": "#ef4444"
    },
    {
      "lat": 14.691939,
      "lng": -17.444084,
      "gate_ref": "G6",
      "color": "#ef4444"
    },
    {
      "lat": 14.691392,
      "lng": -17.44415,
      "gate_ref": "G6",
      "color": "#ef4444"
    },
    {
      "lat": 14.692,
      "lng": -17.444214,
      "gate_ref": "G6",
      "color": "#ef4444"
    },
    {
      "lat": 14.691434,
      "lng": -17.444203,
      "gate_ref": "G6",
      "color": "#ef4444"
    },
    {
      "lat": 14.691831,
      "lng": -17.443989,
      "gate_ref": "G6",
      "color": "#ef4444"
    },
    {
      "lat": 14.691676,
      "lng": -17.44417,
      "gate_ref": "G6",
      "color": "#ef4444"
    },
    {
      "lat": 14.691989,
      "lng": -17.444023,
      "gate_ref": "G6",
      "color": "#ef4444"
    },
    {
      "lat": 14.691305,
      "lng": -17.444203,
      "gate_ref": "G6",
      "color": "#ef4444"
    },
    {
      "lat": 14.691319,
      "lng": -17.444142,
      "gate_ref": "G6",
      "color": "#ef4444"
    },
    {
      "lat": 14.691909,
      "lng": -17.444101,
      "gate_ref": "G6",
      "color": "#ef4444"
    },
    {
      "lat": 14.691986,
      "lng": -17.444253,
      "gate_ref": "G6",
      "color": "#ef4444"
    },
    {
      "lat": 14.69094,
      "lng": -17.444046,
      "gate_ref": "G6",
      "color": "#ef4444"
    },
    {
      "lat": 14.691993,
      "lng": -17.444344,
      "gate_ref": "G6",
      "color": "#ef4444"
    },
    {
      "lat": 14.691751,
      "lng": -17.444036,
      "gate_ref": "G6",
      "color": "#ef4444"
    },
    {
      "lat": 14.691766,
      "lng": -17.444134,
      "gate_ref": "G6",
      "color": "#ef4444"
    },
    {
      "lat": 14.691333,
      "lng": -17.444192,
      "gate_ref": "G6",
      "color": "#ef4444"
    },
    {
      "lat": 14.691672,
      "lng": -17.444135,
      "gate_ref": "G6",
      "color": "#ef4444"
    },
    {
      "lat": 14.691363,
      "lng": -17.443985,
      "gate_ref": "G6",
      "color": "#ef4444"
    },
    {
      "lat": 14.69179,
      "lng": -17.444209,
      "gate_ref": "G6",
      "color": "#ef4444"
    },
    {
      "lat": 14.691983,
      "lng": -17.44413,
      "gate_ref": "G6",
      "color": "#ef4444"
    },
    {
      "lat": 14.691205,
      "lng": -17.444041,
      "gate_ref": "G6",
      "color": "#ef4444"
    },
    {
      "lat": 14.691455,
      "lng": -17.444146,
      "gate_ref": "G6",
      "color": "#ef4444"
    },
    {
      "lat": 14.691987,
      "lng": -17.444526,
      "gate_ref": "G6",
      "color": "#ef4444"
    },
    {
      "lat": 14.691819,
      "lng": -17.443961,
      "gate_ref": "G6",
      "color": "#ef4444"
    },
    {
      "lat": 14.691115,
      "lng": -17.444046,
      "gate_ref": "G6",
      "color": "#ef4444"
    },
    {
      "lat": 14.691112,
      "lng": -17.444057,
      "gate_ref": "G6",
      "color": "#ef4444"
    },
    {
      "lat": 14.691317,
      "lng": -17.444215,
      "gate_ref": "G6",
      "color": "#ef4444"
    },
    {
      "lat": 14.69137,
      "lng": -17.443967,
      "gate_ref": "G6",
      "color": "#ef4444"
    },
    {
      "lat": 14.691927,
      "lng": -17.444139,
      "gate_ref": "G6",
      "color": "#ef4444"
    },
    {
      "lat": 14.691705,
      "lng": -17.444074,
      "gate_ref": "G6",
      "color": "#ef4444"
    },
    {
      "lat": 14.691905,
      "lng": -17.44396,
      "gate_ref": "G6",
      "color": "#ef4444"
    },
    {
      "lat": 14.6918,
      "lng": -17.444133,
      "gate_ref": "G6",
      "color": "#ef4444"
    },
    {
      "lat": 14.691503,
      "lng": -17.443958,
      "gate_ref": "G6",
      "color": "#ef4444"
    },
    {
      "lat": 14.691144,
      "lng": -17.444028,
      "gate_ref": "G6",
      "color": "#ef4444"
    },
    {
      "lat": 14.692,
      "lng": -17.444054,
      "gate_ref": "G6",
      "color": "#ef4444"
    },
    {
      "lat": 14.691399,
      "lng": -17.444142,
      "gate_ref": "G6",
      "color": "#ef4444"
    },
    {
      "lat": 14.691675,
      "lng": -17.4442,
      "gate_ref": "G6",
      "color": "#ef4444"
    },
    {
      "lat": 14.691144,
      "lng": -17.444013,
      "gate_ref": "G6",
      "color": "#ef4444"
    },
    {
      "lat": 14.691756,
      "lng": -17.444147,
      "gate_ref": "G6",
      "color": "#ef4444"
    },
    {
      "lat": 14.691358,
      "lng": -17.444086,
      "gate_ref": "G6",
      "color": "#ef4444"
    },
    {
      "lat": 14.691688,
      "lng": -17.444084,
      "gate_ref": "G6",
      "color": "#ef4444"
    },
    {
      "lat": 14.691885,
      "lng": -17.44419,
      "gate_ref": "G6",
      "color": "#ef4444"
    },
    {
      "lat": 14.691794,
      "lng": -17.444197,
      "gate_ref": "G6",
      "color": "#ef4444"
    },
    {
      "lat": 14.691383,
      "lng": -17.444184,
      "gate_ref": "G6",
      "color": "#ef4444"
    },
    {
      "lat": 14.691998,
      "lng": -17.444085,
      "gate_ref": "G6",
      "color": "#ef4444"
    },
    {
      "lat": 14.691524,
      "lng": -17.444239,
      "gate_ref": "G6",
      "color": "#ef4444"
    },
    {
      "lat": 14.691908,
      "lng": -17.443493,
      "gate_ref": "G6",
      "color": "#ef4444"
    },
    {
      "lat": 14.692083,
      "lng": -17.443568,
      "gate_ref": "G6",
      "color": "#ef4444"
    },
    {
      "lat": 14.691842,
      "lng": -17.444181,
      "gate_ref": "G6",
      "color": "#ef4444"
    },
    {
      "lat": 14.691928,
      "lng": -17.444143,
      "gate_ref": "G6",
      "color": "#ef4444"
    },
    {
      "lat": 14.691554,
      "lng": -17.444207,
      "gate_ref": "G6",
      "color": "#ef4444"
    },
    {
      "lat": 14.691348,
      "lng": -17.444178,
      "gate_ref": "G6",
      "color": "#ef4444"
    },
    {
      "lat": 14.691891,
      "lng": -17.444543,
      "gate_ref": "G6",
      "color": "#ef4444"
    },
    {
      "lat": 14.691316,
      "lng": -17.444054,
      "gate_ref": "G6",
      "color": "#ef4444"
    },
    {
      "lat": 14.691987,
      "lng": -17.444072,
      "gate_ref": "G6",
      "color": "#ef4444"
    },
    {
      "lat": 14.691334,
      "lng": -17.444187,
      "gate_ref": "G6",
      "color": "#ef4444"
    },
    {
      "lat": 14.691982,
      "lng": -17.444025,
      "gate_ref": "G6",
      "color": "#ef4444"
    },
    {
      "lat": 14.691305,
      "lng": -17.443962,
      "gate_ref": "G6",
      "color": "#ef4444"
    },
    {
      "lat": 14.691993,
      "lng": -17.444101,
      "gate_ref": "G6",
      "color": "#ef4444"
    },
    {
      "lat": 14.691665,
      "lng": -17.444218,
      "gate_ref": "G6",
      "color": "#ef4444"
    },
    {
      "lat": 14.691363,
      "lng": -17.444044,
      "gate_ref": "G6",
      "color": "#ef4444"
    },
    {
      "lat": 14.691978,
      "lng": -17.444554,
      "gate_ref": "G6",
      "color": "#ef4444"
    },
    {
      "lat": 14.69171,
      "lng": -17.443974,
      "gate_ref": "G6",
      "color": "#ef4444"
    },
    {
      "lat": 14.691008,
      "lng": -17.444228,
      "gate_ref": "G6",
      "color": "#ef4444"
    },
    {
      "lat": 14.691872,
      "lng": -17.443962,
      "gate_ref": "G6",
      "color": "#ef4444"
    },
    {
      "lat": 14.691882,
      "lng": -17.444169,
      "gate_ref": "G6",
      "color": "#ef4444"
    },
    {
      "lat": 14.69109,
      "lng": -17.444138,
      "gate_ref": "G6",
      "color": "#ef4444"
    },
    {
      "lat": 14.691843,
      "lng": -17.443992,
      "gate_ref": "G6",
      "color": "#ef4444"
    },
    {
      "lat": 14.691737,
      "lng": -17.444045,
      "gate_ref": "G6",
      "color": "#ef4444"
    },
    {
      "lat": 14.691995,
      "lng": -17.444116,
      "gate_ref": "G6",
      "color": "#ef4444"
    },
    {
      "lat": 14.691916,
      "lng": -17.444132,
      "gate_ref": "G6",
      "color": "#ef4444"
    },
    {
      "lat": 14.691495,
      "lng": -17.443969,
      "gate_ref": "G6",
      "color": "#ef4444"
    },
    {
      "lat": 14.691979,
      "lng": -17.443959,
      "gate_ref": "G6",
      "color": "#ef4444"
    },
    {
      "lat": 14.691998,
      "lng": -17.443989,
      "gate_ref": "G6",
      "color": "#ef4444"
    },
    {
      "lat": 14.691892,
      "lng": -17.444105,
      "gate_ref": "G6",
      "color": "#ef4444"
    },
    {
      "lat": 14.691452,
      "lng": -17.444021,
      "gate_ref": "G6",
      "color": "#ef4444"
    },
    {
      "lat": 14.691566,
      "lng": -17.444055,
      "gate_ref": "G6",
      "color": "#ef4444"
    },
    {
      "lat": 14.69187,
      "lng": -17.444075,
      "gate_ref": "G6",
      "color": "#ef4444"
    },
    {
      "lat": 14.691917,
      "lng": -17.444222,
      "gate_ref": "G6",
      "color": "#ef4444"
    },
    {
      "lat": 14.691322,
      "lng": -17.44412,
      "gate_ref": "G6",
      "color": "#ef4444"
    },
    {
      "lat": 14.691826,
      "lng": -17.444174,
      "gate_ref": "G6",
      "color": "#ef4444"
    },
    {
      "lat": 14.691011,
      "lng": -17.444086,
      "gate_ref": "G6",
      "color": "#ef4444"
    },
    {
      "lat": 14.691444,
      "lng": -17.444132,
      "gate_ref": "G6",
      "color": "#ef4444"
    },
    {
      "lat": 14.691746,
      "lng": -17.444027,
      "gate_ref": "G6",
      "color": "#ef4444"
    },
    {
      "lat": 14.691489,
      "lng": -17.44409,
      "gate_ref": "G6",
      "color": "#ef4444"
    },
    {
      "lat": 14.692088,
      "lng": -17.44363,
      "gate_ref": "G6",
      "color": "#ef4444"
    },
    {
      "lat": 14.691998,
      "lng": -17.444027,
      "gate_ref": "G6",
      "color": "#ef4444"
    },
    {
      "lat": 14.691866,
      "lng": -17.443823,
      "gate_ref": "G6",
      "color": "#ef4444"
    },
    {
      "lat": 14.692034,
      "lng": -17.444292,
      "gate_ref": "G6",
      "color": "#ef4444"
    },
    {
      "lat": 14.691328,
      "lng": -17.443979,
      "gate_ref": "G6",
      "color": "#ef4444"
    },
    {
      "lat": 14.691859,
      "lng": -17.444044,
      "gate_ref": "G6",
      "color": "#ef4444"
    },
    {
      "lat": 14.691269,
      "lng": -17.443961,
      "gate_ref": "G6",
      "color": "#ef4444"
    },
    {
      "lat": 14.691817,
      "lng": -17.444146,
      "gate_ref": "G6",
      "color": "#ef4444"
    },
    {
      "lat": 14.691944,
      "lng": -17.4437,
      "gate_ref": "G6",
      "color": "#ef4444"
    },
    {
      "lat": 14.691795,
      "lng": -17.444052,
      "gate_ref": "G6",
      "color": "#ef4444"
    },
    {
      "lat": 14.691811,
      "lng": -17.44417,
      "gate_ref": "G6",
      "color": "#ef4444"
    },
    {
      "lat": 14.691828,
      "lng": -17.44418,
      "gate_ref": "G6",
      "color": "#ef4444"
    },
    {
      "lat": 14.691849,
      "lng": -17.444214,
      "gate_ref": "G6",
      "color": "#ef4444"
    },
    {
      "lat": 14.691589,
      "lng": -17.443984,
      "gate_ref": "G6",
      "color": "#ef4444"
    },
    {
      "lat": 14.691725,
      "lng": -17.44418,
      "gate_ref": "G6",
      "color": "#ef4444"
    },
    {
      "lat": 14.691367,
      "lng": -17.443964,
      "gate_ref": "G6",
      "color": "#ef4444"
    },
    {
      "lat": 14.691482,
      "lng": -17.443999,
      "gate_ref": "G6",
      "color": "#ef4444"
    },
    {
      "lat": 14.691857,
      "lng": -17.445956,
      "gate_ref": "G7",
      "color": "#ef4444"
    },
    {
      "lat": 14.691545,
      "lng": -17.44622,
      "gate_ref": "G7",
      "color": "#ef4444"
    },
    {
      "lat": 14.691639,
      "lng": -17.446103,
      "gate_ref": "G7",
      "color": "#ef4444"
    },
    {
      "lat": 14.692033,
      "lng": -17.445795,
      "gate_ref": "G7",
      "color": "#ef4444"
    },
    {
      "lat": 14.692169,
      "lng": -17.445886,
      "gate_ref": "G7",
      "color": "#ef4444"
    },
    {
      "lat": 14.691633,
      "lng": -17.445436,
      "gate_ref": "G7",
      "color": "#ef4444"
    },
    {
      "lat": 14.691879,
      "lng": -17.446174,
      "gate_ref": "G7",
      "color": "#ef4444"
    },
    {
      "lat": 14.691676,
      "lng": -17.446051,
      "gate_ref": "G7",
      "color": "#ef4444"
    },
    {
      "lat": 14.692022,
      "lng": -17.446067,
      "gate_ref": "G7",
      "color": "#ef4444"
    },
    {
      "lat": 14.692136,
      "lng": -17.445851,
      "gate_ref": "G7",
      "color": "#ef4444"
    },
    {
      "lat": 14.691677,
      "lng": -17.446254,
      "gate_ref": "G7",
      "color": "#ef4444"
    },
    {
      "lat": 14.691971,
      "lng": -17.44576,
      "gate_ref": "G7",
      "color": "#ef4444"
    },
    {
      "lat": 14.692183,
      "lng": -17.445911,
      "gate_ref": "G7",
      "color": "#ef4444"
    },
    {
      "lat": 14.691696,
      "lng": -17.44641,
      "gate_ref": "G7",
      "color": "#ef4444"
    },
    {
      "lat": 14.691447,
      "lng": -17.446666,
      "gate_ref": "G7",
      "color": "#ef4444"
    },
    {
      "lat": 14.692159,
      "lng": -17.445864,
      "gate_ref": "G7",
      "color": "#ef4444"
    },
    {
      "lat": 14.691497,
      "lng": -17.446244,
      "gate_ref": "G7",
      "color": "#ef4444"
    },
    {
      "lat": 14.691444,
      "lng": -17.446482,
      "gate_ref": "G7",
      "color": "#ef4444"
    },
    {
      "lat": 14.691704,
      "lng": -17.446318,
      "gate_ref": "G7",
      "color": "#ef4444"
    },
    {
      "lat": 14.69202,
      "lng": -17.445812,
      "gate_ref": "G7",
      "color": "#ef4444"
    },
    {
      "lat": 14.691791,
      "lng": -17.446089,
      "gate_ref": "G7",
      "color": "#ef4444"
    },
    {
      "lat": 14.692015,
      "lng": -17.44585,
      "gate_ref": "G7",
      "color": "#ef4444"
    },
    {
      "lat": 14.692522,
      "lng": -17.44609,
      "gate_ref": "G7",
      "color": "#ef4444"
    },
    {
      "lat": 14.6914,
      "lng": -17.446401,
      "gate_ref": "G7",
      "color": "#ef4444"
    },
    {
      "lat": 14.691785,
      "lng": -17.445989,
      "gate_ref": "G7",
      "color": "#ef4444"
    },
    {
      "lat": 14.692038,
      "lng": -17.445773,
      "gate_ref": "G7",
      "color": "#ef4444"
    },
    {
      "lat": 14.691616,
      "lng": -17.446186,
      "gate_ref": "G7",
      "color": "#ef4444"
    },
    {
      "lat": 14.691747,
      "lng": -17.446112,
      "gate_ref": "G7",
      "color": "#ef4444"
    },
    {
      "lat": 14.691948,
      "lng": -17.445904,
      "gate_ref": "G7",
      "color": "#ef4444"
    },
    {
      "lat": 14.692364,
      "lng": -17.446246,
      "gate_ref": "G7",
      "color": "#ef4444"
    },
    {
      "lat": 14.692036,
      "lng": -17.445966,
      "gate_ref": "G7",
      "color": "#ef4444"
    },
    {
      "lat": 14.692509,
      "lng": -17.446305,
      "gate_ref": "G7",
      "color": "#ef4444"
    },
    {
      "lat": 14.691951,
      "lng": -17.445944,
      "gate_ref": "G7",
      "color": "#ef4444"
    },
    {
      "lat": 14.692096,
      "lng": -17.445877,
      "gate_ref": "G7",
      "color": "#ef4444"
    },
    {
      "lat": 14.692323,
      "lng": -17.445864,
      "gate_ref": "G7",
      "color": "#ef4444"
    },
    {
      "lat": 14.69242,
      "lng": -17.446257,
      "gate_ref": "G7",
      "color": "#ef4444"
    },
    {
      "lat": 14.691694,
      "lng": -17.446097,
      "gate_ref": "G7",
      "color": "#ef4444"
    },
    {
      "lat": 14.691499,
      "lng": -17.446404,
      "gate_ref": "G7",
      "color": "#ef4444"
    },
    {
      "lat": 14.691767,
      "lng": -17.445983,
      "gate_ref": "G7",
      "color": "#ef4444"
    },
    {
      "lat": 14.69212,
      "lng": -17.445867,
      "gate_ref": "G7",
      "color": "#ef4444"
    },
    {
      "lat": 14.691609,
      "lng": -17.446486,
      "gate_ref": "G7",
      "color": "#ef4444"
    },
    {
      "lat": 14.691947,
      "lng": -17.446021,
      "gate_ref": "G7",
      "color": "#ef4444"
    },
    {
      "lat": 14.692175,
      "lng": -17.445913,
      "gate_ref": "G7",
      "color": "#ef4444"
    },
    {
      "lat": 14.692423,
      "lng": -17.446024,
      "gate_ref": "G7",
      "color": "#ef4444"
    },
    {
      "lat": 14.691992,
      "lng": -17.445976,
      "gate_ref": "G7",
      "color": "#ef4444"
    },
    {
      "lat": 14.692114,
      "lng": -17.445817,
      "gate_ref": "G7",
      "color": "#ef4444"
    },
    {
      "lat": 14.692541,
      "lng": -17.446044,
      "gate_ref": "G7",
      "color": "#ef4444"
    },
    {
      "lat": 14.692371,
      "lng": -17.445899,
      "gate_ref": "G7",
      "color": "#ef4444"
    },
    {
      "lat": 14.692188,
      "lng": -17.445889,
      "gate_ref": "G7",
      "color": "#ef4444"
    },
    {
      "lat": 14.691962,
      "lng": -17.445803,
      "gate_ref": "G7",
      "color": "#ef4444"
    },
    {
      "lat": 14.691596,
      "lng": -17.446439,
      "gate_ref": "G7",
      "color": "#ef4444"
    },
    {
      "lat": 14.691488,
      "lng": -17.446354,
      "gate_ref": "G7",
      "color": "#ef4444"
    },
    {
      "lat": 14.691673,
      "lng": -17.446066,
      "gate_ref": "G7",
      "color": "#ef4444"
    },
    {
      "lat": 14.691467,
      "lng": -17.446455,
      "gate_ref": "G7",
      "color": "#ef4444"
    },
    {
      "lat": 14.691594,
      "lng": -17.446181,
      "gate_ref": "G7",
      "color": "#ef4444"
    },
    {
      "lat": 14.691322,
      "lng": -17.446465,
      "gate_ref": "G7",
      "color": "#ef4444"
    },
    {
      "lat": 14.691523,
      "lng": -17.446455,
      "gate_ref": "G7",
      "color": "#ef4444"
    },
    {
      "lat": 14.691933,
      "lng": -17.445803,
      "gate_ref": "G7",
      "color": "#ef4444"
    },
    {
      "lat": 14.691709,
      "lng": -17.446022,
      "gate_ref": "G7",
      "color": "#ef4444"
    },
    {
      "lat": 14.691551,
      "lng": -17.446358,
      "gate_ref": "G7",
      "color": "#ef4444"
    },
    {
      "lat": 14.692133,
      "lng": -17.445949,
      "gate_ref": "G7",
      "color": "#ef4444"
    },
    {
      "lat": 14.692088,
      "lng": -17.445802,
      "gate_ref": "G7",
      "color": "#ef4444"
    },
    {
      "lat": 14.69191,
      "lng": -17.44612,
      "gate_ref": "G7",
      "color": "#ef4444"
    },
    {
      "lat": 14.69204,
      "lng": -17.445616,
      "gate_ref": "G7",
      "color": "#ef4444"
    },
    {
      "lat": 14.691451,
      "lng": -17.446686,
      "gate_ref": "G7",
      "color": "#ef4444"
    },
    {
      "lat": 14.691459,
      "lng": -17.446601,
      "gate_ref": "G7",
      "color": "#ef4444"
    },
    {
      "lat": 14.691898,
      "lng": -17.445636,
      "gate_ref": "G7",
      "color": "#ef4444"
    },
    {
      "lat": 14.692378,
      "lng": -17.446192,
      "gate_ref": "G7",
      "color": "#ef4444"
    },
    {
      "lat": 14.692077,
      "lng": -17.445913,
      "gate_ref": "G7",
      "color": "#ef4444"
    },
    {
      "lat": 14.691576,
      "lng": -17.44638,
      "gate_ref": "G7",
      "color": "#ef4444"
    },
    {
      "lat": 14.691826,
      "lng": -17.44609,
      "gate_ref": "G7",
      "color": "#ef4444"
    },
    {
      "lat": 14.691967,
      "lng": -17.445459,
      "gate_ref": "G7",
      "color": "#ef4444"
    },
    {
      "lat": 14.691899,
      "lng": -17.445871,
      "gate_ref": "G7",
      "color": "#ef4444"
    },
    {
      "lat": 14.69215,
      "lng": -17.445859,
      "gate_ref": "G7",
      "color": "#ef4444"
    },
    {
      "lat": 14.691706,
      "lng": -17.446222,
      "gate_ref": "G7",
      "color": "#ef4444"
    },
    {
      "lat": 14.692425,
      "lng": -17.446128,
      "gate_ref": "G7",
      "color": "#ef4444"
    },
    {
      "lat": 14.691879,
      "lng": -17.445625,
      "gate_ref": "G7",
      "color": "#ef4444"
    },
    {
      "lat": 14.691327,
      "lng": -17.446518,
      "gate_ref": "G7",
      "color": "#ef4444"
    },
    {
      "lat": 14.69214,
      "lng": -17.445841,
      "gate_ref": "G7",
      "color": "#ef4444"
    },
    {
      "lat": 14.691672,
      "lng": -17.446331,
      "gate_ref": "G7",
      "color": "#ef4444"
    },
    {
      "lat": 14.691558,
      "lng": -17.446289,
      "gate_ref": "G7",
      "color": "#ef4444"
    },
    {
      "lat": 14.691907,
      "lng": -17.44606,
      "gate_ref": "G7",
      "color": "#ef4444"
    },
    {
      "lat": 14.692159,
      "lng": -17.445873,
      "gate_ref": "G7",
      "color": "#ef4444"
    },
    {
      "lat": 14.691714,
      "lng": -17.446383,
      "gate_ref": "G7",
      "color": "#ef4444"
    },
    {
      "lat": 14.691484,
      "lng": -17.446405,
      "gate_ref": "G7",
      "color": "#ef4444"
    },
    {
      "lat": 14.692064,
      "lng": -17.445764,
      "gate_ref": "G7",
      "color": "#ef4444"
    },
    {
      "lat": 14.692067,
      "lng": -17.445857,
      "gate_ref": "G7",
      "color": "#ef4444"
    },
    {
      "lat": 14.692325,
      "lng": -17.446048,
      "gate_ref": "G7",
      "color": "#ef4444"
    },
    {
      "lat": 14.691942,
      "lng": -17.446163,
      "gate_ref": "G7",
      "color": "#ef4444"
    },
    {
      "lat": 14.69195,
      "lng": -17.446134,
      "gate_ref": "G7",
      "color": "#ef4444"
    },
    {
      "lat": 14.692054,
      "lng": -17.445851,
      "gate_ref": "G7",
      "color": "#ef4444"
    },
    {
      "lat": 14.691909,
      "lng": -17.445936,
      "gate_ref": "G7",
      "color": "#ef4444"
    },
    {
      "lat": 14.691817,
      "lng": -17.446282,
      "gate_ref": "G7",
      "color": "#ef4444"
    },
    {
      "lat": 14.692501,
      "lng": -17.446102,
      "gate_ref": "G7",
      "color": "#ef4444"
    },
    {
      "lat": 14.691343,
      "lng": -17.446514,
      "gate_ref": "G7",
      "color": "#ef4444"
    },
    {
      "lat": 14.692434,
      "lng": -17.446218,
      "gate_ref": "G7",
      "color": "#ef4444"
    },
    {
      "lat": 14.691764,
      "lng": -17.446152,
      "gate_ref": "G7",
      "color": "#ef4444"
    },
    {
      "lat": 14.692146,
      "lng": -17.44591,
      "gate_ref": "G7",
      "color": "#ef4444"
    },
    {
      "lat": 14.691971,
      "lng": -17.44599,
      "gate_ref": "G7",
      "color": "#ef4444"
    },
    {
      "lat": 14.691938,
      "lng": -17.445984,
      "gate_ref": "G7",
      "color": "#ef4444"
    },
    {
      "lat": 14.691997,
      "lng": -17.446,
      "gate_ref": "G7",
      "color": "#ef4444"
    },
    {
      "lat": 14.691869,
      "lng": -17.446023,
      "gate_ref": "G7",
      "color": "#ef4444"
    },
    {
      "lat": 14.691704,
      "lng": -17.446042,
      "gate_ref": "G7",
      "color": "#ef4444"
    },
    {
      "lat": 14.692052,
      "lng": -17.445687,
      "gate_ref": "G7",
      "color": "#ef4444"
    },
    {
      "lat": 14.692431,
      "lng": -17.446146,
      "gate_ref": "G7",
      "color": "#ef4444"
    },
    {
      "lat": 14.691388,
      "lng": -17.446489,
      "gate_ref": "G7",
      "color": "#ef4444"
    },
    {
      "lat": 14.69242,
      "lng": -17.446097,
      "gate_ref": "G7",
      "color": "#ef4444"
    },
    {
      "lat": 14.692025,
      "lng": -17.446006,
      "gate_ref": "G7",
      "color": "#ef4444"
    },
    {
      "lat": 14.691946,
      "lng": -17.445494,
      "gate_ref": "G7",
      "color": "#ef4444"
    },
    {
      "lat": 14.691902,
      "lng": -17.446106,
      "gate_ref": "G7",
      "color": "#ef4444"
    },
    {
      "lat": 14.693598,
      "lng": -17.446215,
      "gate_ref": "G8",
      "color": "#f97316"
    },
    {
      "lat": 14.693633,
      "lng": -17.44638,
      "gate_ref": "G8",
      "color": "#f97316"
    },
    {
      "lat": 14.693723,
      "lng": -17.446717,
      "gate_ref": "G8",
      "color": "#f97316"
    },
    {
      "lat": 14.693573,
      "lng": -17.446904,
      "gate_ref": "G8",
      "color": "#f97316"
    },
    {
      "lat": 14.693701,
      "lng": -17.446211,
      "gate_ref": "G8",
      "color": "#f97316"
    },
    {
      "lat": 14.693717,
      "lng": -17.447218,
      "gate_ref": "G8",
      "color": "#f97316"
    },
    {
      "lat": 14.693729,
      "lng": -17.446267,
      "gate_ref": "G8",
      "color": "#f97316"
    },
    {
      "lat": 14.693671,
      "lng": -17.446834,
      "gate_ref": "G8",
      "color": "#f97316"
    },
    {
      "lat": 14.693645,
      "lng": -17.446884,
      "gate_ref": "G8",
      "color": "#f97316"
    },
    {
      "lat": 14.69377,
      "lng": -17.4462,
      "gate_ref": "G8",
      "color": "#f97316"
    },
    {
      "lat": 14.693839,
      "lng": -17.446608,
      "gate_ref": "G8",
      "color": "#f97316"
    },
    {
      "lat": 14.693592,
      "lng": -17.446234,
      "gate_ref": "G8",
      "color": "#f97316"
    },
    {
      "lat": 14.69369,
      "lng": -17.446222,
      "gate_ref": "G8",
      "color": "#f97316"
    },
    {
      "lat": 14.693729,
      "lng": -17.44664,
      "gate_ref": "G8",
      "color": "#f97316"
    },
    {
      "lat": 14.693611,
      "lng": -17.446281,
      "gate_ref": "G8",
      "color": "#f97316"
    },
    {
      "lat": 14.693926,
      "lng": -17.446275,
      "gate_ref": "G8",
      "color": "#f97316"
    },
    {
      "lat": 14.693777,
      "lng": -17.446835,
      "gate_ref": "G8",
      "color": "#f97316"
    },
    {
      "lat": 14.693729,
      "lng": -17.446917,
      "gate_ref": "G8",
      "color": "#f97316"
    },
    {
      "lat": 14.693647,
      "lng": -17.44606,
      "gate_ref": "G8",
      "color": "#f97316"
    },
    {
      "lat": 14.693737,
      "lng": -17.447336,
      "gate_ref": "G8",
      "color": "#f97316"
    },
    {
      "lat": 14.693564,
      "lng": -17.44622,
      "gate_ref": "G8",
      "color": "#f97316"
    },
    {
      "lat": 14.693623,
      "lng": -17.446208,
      "gate_ref": "G8",
      "color": "#f97316"
    },
    {
      "lat": 14.693782,
      "lng": -17.446763,
      "gate_ref": "G8",
      "color": "#f97316"
    },
    {
      "lat": 14.69378,
      "lng": -17.447169,
      "gate_ref": "G8",
      "color": "#f97316"
    },
    {
      "lat": 14.693662,
      "lng": -17.446679,
      "gate_ref": "G8",
      "color": "#f97316"
    },
    {
      "lat": 14.693616,
      "lng": -17.446282,
      "gate_ref": "G8",
      "color": "#f97316"
    },
    {
      "lat": 14.693073,
      "lng": -17.446125,
      "gate_ref": "G8",
      "color": "#f97316"
    },
    {
      "lat": 14.693738,
      "lng": -17.44654,
      "gate_ref": "G8",
      "color": "#f97316"
    },
    {
      "lat": 14.694141,
      "lng": -17.446302,
      "gate_ref": "G8",
      "color": "#f97316"
    },
    {
      "lat": 14.693636,
      "lng": -17.447049,
      "gate_ref": "G8",
      "color": "#f97316"
    },
    {
      "lat": 14.693816,
      "lng": -17.4469,
      "gate_ref": "G8",
      "color": "#f97316"
    },
    {
      "lat": 14.693737,
      "lng": -17.446878,
      "gate_ref": "G8",
      "color": "#f97316"
    },
    {
      "lat": 14.693582,
      "lng": -17.446204,
      "gate_ref": "G8",
      "color": "#f97316"
    },
    {
      "lat": 14.693807,
      "lng": -17.446224,
      "gate_ref": "G8",
      "color": "#f97316"
    },
    {
      "lat": 14.693766,
      "lng": -17.447286,
      "gate_ref": "G8",
      "color": "#f97316"
    },
    {
      "lat": 14.693687,
      "lng": -17.446576,
      "gate_ref": "G8",
      "color": "#f97316"
    },
    {
      "lat": 14.693423,
      "lng": -17.446152,
      "gate_ref": "G8",
      "color": "#f97316"
    },
    {
      "lat": 14.693589,
      "lng": -17.446323,
      "gate_ref": "G8",
      "color": "#f97316"
    },
    {
      "lat": 14.69368,
      "lng": -17.447043,
      "gate_ref": "G8",
      "color": "#f97316"
    },
    {
      "lat": 14.693581,
      "lng": -17.446771,
      "gate_ref": "G8",
      "color": "#f97316"
    },
    {
      "lat": 14.693163,
      "lng": -17.446088,
      "gate_ref": "G8",
      "color": "#f97316"
    },
    {
      "lat": 14.693706,
      "lng": -17.446366,
      "gate_ref": "G8",
      "color": "#f97316"
    },
    {
      "lat": 14.693808,
      "lng": -17.447123,
      "gate_ref": "G8",
      "color": "#f97316"
    },
    {
      "lat": 14.693578,
      "lng": -17.447317,
      "gate_ref": "G8",
      "color": "#f97316"
    },
    {
      "lat": 14.693574,
      "lng": -17.446181,
      "gate_ref": "G8",
      "color": "#f97316"
    },
    {
      "lat": 14.693093,
      "lng": -17.446194,
      "gate_ref": "G8",
      "color": "#f97316"
    },
    {
      "lat": 14.69369,
      "lng": -17.446403,
      "gate_ref": "G8",
      "color": "#f97316"
    },
    {
      "lat": 14.693727,
      "lng": -17.446751,
      "gate_ref": "G8",
      "color": "#f97316"
    },
    {
      "lat": 14.693772,
      "lng": -17.44624,
      "gate_ref": "G8",
      "color": "#f97316"
    },
    {
      "lat": 14.69376,
      "lng": -17.44654,
      "gate_ref": "G8",
      "color": "#f97316"
    },
    {
      "lat": 14.693701,
      "lng": -17.446265,
      "gate_ref": "G8",
      "color": "#f97316"
    },
    {
      "lat": 14.693687,
      "lng": -17.446492,
      "gate_ref": "G8",
      "color": "#f97316"
    },
    {
      "lat": 14.693821,
      "lng": -17.446541,
      "gate_ref": "G8",
      "color": "#f97316"
    },
    {
      "lat": 14.693568,
      "lng": -17.447217,
      "gate_ref": "G8",
      "color": "#f97316"
    },
    {
      "lat": 14.693795,
      "lng": -17.447097,
      "gate_ref": "G8",
      "color": "#f97316"
    },
    {
      "lat": 14.69361,
      "lng": -17.44723,
      "gate_ref": "G8",
      "color": "#f97316"
    },
    {
      "lat": 14.693766,
      "lng": -17.447314,
      "gate_ref": "G8",
      "color": "#f97316"
    },
    {
      "lat": 14.69363,
      "lng": -17.446218,
      "gate_ref": "G8",
      "color": "#f97316"
    },
    {
      "lat": 14.694023,
      "lng": -17.446091,
      "gate_ref": "G8",
      "color": "#f97316"
    },
    {
      "lat": 14.69382,
      "lng": -17.446666,
      "gate_ref": "G8",
      "color": "#f97316"
    },
    {
      "lat": 14.693582,
      "lng": -17.446966,
      "gate_ref": "G8",
      "color": "#f97316"
    },
    {
      "lat": 14.693828,
      "lng": -17.446233,
      "gate_ref": "G8",
      "color": "#f97316"
    },
    {
      "lat": 14.693611,
      "lng": -17.446691,
      "gate_ref": "G8",
      "color": "#f97316"
    },
    {
      "lat": 14.693833,
      "lng": -17.4462,
      "gate_ref": "G8",
      "color": "#f97316"
    },
    {
      "lat": 14.694115,
      "lng": -17.446125,
      "gate_ref": "G8",
      "color": "#f97316"
    },
    {
      "lat": 14.694394,
      "lng": -17.446337,
      "gate_ref": "G8",
      "color": "#f97316"
    },
    {
      "lat": 14.693615,
      "lng": -17.446219,
      "gate_ref": "G8",
      "color": "#f97316"
    },
    {
      "lat": 14.693021,
      "lng": -17.446329,
      "gate_ref": "G8",
      "color": "#f97316"
    },
    {
      "lat": 14.693794,
      "lng": -17.447112,
      "gate_ref": "G8",
      "color": "#f97316"
    },
    {
      "lat": 14.693588,
      "lng": -17.446824,
      "gate_ref": "G8",
      "color": "#f97316"
    },
    {
      "lat": 14.693584,
      "lng": -17.446232,
      "gate_ref": "G8",
      "color": "#f97316"
    },
    {
      "lat": 14.693692,
      "lng": -17.44642,
      "gate_ref": "G8",
      "color": "#f97316"
    },
    {
      "lat": 14.693617,
      "lng": -17.44709,
      "gate_ref": "G8",
      "color": "#f97316"
    },
    {
      "lat": 14.693731,
      "lng": -17.447022,
      "gate_ref": "G8",
      "color": "#f97316"
    },
    {
      "lat": 14.693687,
      "lng": -17.447185,
      "gate_ref": "G8",
      "color": "#f97316"
    },
    {
      "lat": 14.69361,
      "lng": -17.446453,
      "gate_ref": "G8",
      "color": "#f97316"
    },
    {
      "lat": 14.69375,
      "lng": -17.446855,
      "gate_ref": "G8",
      "color": "#f97316"
    },
    {
      "lat": 14.693829,
      "lng": -17.446306,
      "gate_ref": "G8",
      "color": "#f97316"
    },
    {
      "lat": 14.693735,
      "lng": -17.447008,
      "gate_ref": "G8",
      "color": "#f97316"
    },
    {
      "lat": 14.693736,
      "lng": -17.4467,
      "gate_ref": "G8",
      "color": "#f97316"
    },
    {
      "lat": 14.693654,
      "lng": -17.446419,
      "gate_ref": "G8",
      "color": "#f97316"
    },
    {
      "lat": 14.693718,
      "lng": -17.446205,
      "gate_ref": "G8",
      "color": "#f97316"
    },
    {
      "lat": 14.69373,
      "lng": -17.446398,
      "gate_ref": "G8",
      "color": "#f97316"
    },
    {
      "lat": 14.693702,
      "lng": -17.446156,
      "gate_ref": "G8",
      "color": "#f97316"
    },
    {
      "lat": 14.693782,
      "lng": -17.446248,
      "gate_ref": "G8",
      "color": "#f97316"
    }
  ],
  "bins": [
    {
      "id": "B1",
      "lat": 14.6957,
      "lng": -17.4462,
      "near_gate": "G1",
      "label": "Poubelle Nord-Ouest",
      "fill_percent": 33,
      "current_liters": 79,
      "max_liters": 240,
      "level": "moderate",
      "color": "#eab308",
      "alert": false
    },
    {
      "id": "B2",
      "lat": 14.6958,
      "lng": -17.4441,
      "near_gate": "G2",
      "label": "Poubelle Nord",
      "fill_percent": 28,
      "current_liters": 67,
      "max_liters": 240,
      "level": "moderate",
      "color": "#eab308",
      "alert": false
    },
    {
      "id": "B3",
      "lat": 14.6957,
      "lng": -17.442,
      "near_gate": "G3",
      "label": "Poubelle Nord-Est",
      "fill_percent": 23,
      "current_liters": 55,
      "max_liters": 240,
      "level": "low",
      "color": "#22c55e",
      "alert": false
    },
    {
      "id": "B4",
      "lat": 14.6937,
      "lng": -17.4412,
      "near_gate": "G4",
      "label": "Poubelle Est",
      "fill_percent": 38,
      "current_liters": 91,
      "max_liters": 240,
      "level": "moderate",
      "color": "#eab308",
      "alert": false
    },
    {
      "id": "B5",
      "lat": 14.6916,
      "lng": -17.442,
      "near_gate": "G5",
      "label": "Poubelle Sud-Est",
      "fill_percent": 36,
      "current_liters": 86,
      "max_liters": 240,
      "level": "moderate",
      "color": "#eab308",
      "alert": false
    },
    {
      "id": "B6",
      "lat": 14.6914,
      "lng": -17.4441,
      "near_gate": "G6",
      "label": "Poubelle Sud",
      "fill_percent": 48,
      "current_liters": 115,
      "max_liters": 240,
      "level": "moderate",
      "color": "#eab308",
      "alert": false
    },
    {
      "id": "B7",
      "lat": 14.6916,
      "lng": -17.4462,
      "near_gate": "G7",
      "label": "Poubelle Sud-Ouest",
      "fill_percent": 49,
      "current_liters": 118,
      "max_liters": 240,
      "level": "moderate",
      "color": "#eab308",
      "alert": false
    },
    {
      "id": "B8",
      "lat": 14.6937,
      "lng": -17.447,
      "near_gate": "G8",
      "label": "Poubelle Ouest",
      "fill_percent": 37,
      "current_liters": 89,
      "max_liters": 240,
      "level": "moderate",
      "color": "#eab308",
      "alert": false
    },
    {
      "id": "B9",
      "lat": 14.6945,
      "lng": -17.4441,
      "near_gate": "G2",
      "label": "Poubelle Cour Nord",
      "fill_percent": 26,
      "current_liters": 62,
      "max_liters": 240,
      "level": "moderate",
      "color": "#eab308",
      "alert": false
    },
    {
      "id": "B10",
      "lat": 14.6929,
      "lng": -17.4441,
      "near_gate": "G6",
      "label": "Poubelle Cour Sud",
      "fill_percent": 37,
      "current_liters": 89,
      "max_liters": 240,
      "level": "moderate",
      "color": "#eab308",
      "alert": false
    }
  ],
  "alerts": [
    {
      "id": "alert-gate-G1",
      "type": "crowd",
      "name": "Entrée Nord-Ouest",
      "severity": "warning",
      "description": "516 pers. · densité 64%",
      "lat": 14.6952,
      "lng": -17.4458,
      "value": 516
    },
    {
      "id": "alert-gate-G2",
      "type": "crowd",
      "name": "Entrée Nord",
      "severity": "warning",
      "description": "417 pers. · densité 69%",
      "lat": 14.6953,
      "lng": -17.4441,
      "value": 417
    },
    {
      "id": "alert-gate-G3",
      "type": "crowd",
      "name": "Entrée Nord-Est",
      "severity": "warning",
      "description": "416 pers. · densité 59%",
      "lat": 14.6952,
      "lng": -17.4424,
      "value": 416
    },
    {
      "id": "alert-gate-G4",
      "type": "crowd",
      "name": "Entrée Est",
      "severity": "warning",
      "description": "307 pers. · densité 61%",
      "lat": 14.6937,
      "lng": -17.4419,
      "value": 307
    },
    {
      "id": "alert-gate-G5",
      "type": "crowd",
      "name": "Entrée Sud-Est",
      "severity": "critical",
      "description": "548 pers. · densité 78%",
      "lat": 14.6921,
      "lng": -17.4424,
      "value": 548
    },
    {
      "id": "alert-gate-G6",
      "type": "crowd",
      "name": "Entrée Sud",
      "severity": "critical",
      "description": "900 pers. · densité 100%",
      "lat": 14.692,
      "lng": -17.4441,
      "value": 900
    },
    {
      "id": "alert-gate-G7",
      "type": "crowd",
      "name": "Entrée Sud-Ouest",
      "severity": "critical",
      "description": "733 pers. · densité 92%",
      "lat": 14.6921,
      "lng": -17.4458,
      "value": 733
    },
    {
      "id": "alert-gate-G8",
      "type": "crowd",
      "name": "Entrée Ouest",
      "severity": "warning",
      "description": "426 pers. · densité 71%",
      "lat": 14.6937,
      "lng": -17.4462,
      "value": 426
    }
  ],
  "stats": {
    "total_crowd": 4263,
    "max_capacity": 5600,
    "occupancy_rate": 76,
    "critical_bins": 0,
    "active_alerts": 8
  }
}